TorchRegister/__init__.py
TorchRegister/torchregister.py
TorchRegister/utils.py
TorchRegister/warpings.py
TorchRegister-0.2.2.dist-info/LICENSE.md
TorchRegister-0.2.2.dist-info/METADATA
TorchRegister-0.2.2.dist-info/WHEEL
TorchRegister-0.2.2.dist-info/top_level.txt
TorchRegister-0.2.2.dist-info/RECORD
